{"version": 0.6, "generator": "Overpass API 0.7.62.4 2390de5a", "osm3s": {"timestamp_osm_base": "2025-01-08T07:19:43Z", "copyright": "The data included in this document is from www.openstreetmap.org. The data is made available under ODbL."}, "elements": [{"type": "node", "id": 3901504169, "lat": 31.0999166, "lon": -4.0140878, "tags": {"name": "Merzouga \u2d4e\u2d30\u2d54\u2d63\u2d53\u2d33\u2d30 \u0645\u0631\u0632\u0648\u0643\u0629", "name:ar": "\u0645\u0631\u0632\u0648\u0643\u0629", "name:ber": "\u2d4e\u2d30\u2d54\u2d63\u2d53\u2d33\u2d30", "name:de": "Merzouga", "name:en": "Merzouga", "name:fr": "Merzouga", "place": "town", "wikidata": "Q1922278", "wikimedia_commons": "Category:Merzouga", "wikipedia": "de:Merzouga"}}]}