{"version": 0.6, "generator": "Overpass API 0.7.62.4 2390de5a", "osm3s": {"timestamp_osm_base": "2025-01-08T06:28:44Z", "copyright": "The data included in this document is from www.openstreetmap.org. The data is made available under ODbL."}, "elements": [{"type": "node", "id": 186458189, "lat": 36.2684483, "lon": 36.5672311, "tags": {"alt_name:ar": "\u0631\u064a\u062d\u0627\u0646\u064a\u0629", "alt_name:ml": "\u0d05\u0d7c-\u0d31\u0d2f\u0d4d\u0d39\u0d3e\u0d28\u0d3f\u0d2f", "geonames:id": "302355", "name": "Reyhanl\u0131", "name:ar": "\u0627\u0644\u0631\u064a\u062d\u0627\u0646\u064a\u0629", "name:azb": "\u0631\u06cc\u062d\u0627\u0646\u0644\u06cc", "name:ce": "\u0420\u0435\u0439\u0445\u04c0\u0430\u043d\u043b\u0438", "name:ckb": "\u0695\u06d5\u06cc\u062d\u0627\u0646\u06cc", "name:fa": "\u0631\u06cc\u062d\u0627\u0646\u0644\u06cc", "name:ku": "Reyhan\u00ee", "name:ml": "\u0d31\u0d46\u0d2f\u0d4d\u0d39\u0d3e\u0d7b\u0d32\u0d3f", "name:pnb": "\u0631\u06cc\u06c1\u0627\u0646\u0644\u06cc", "name:ru": "\u0420\u0435\u0439\u0445\u0430\u043d\u043b\u044b", "name:sr": "\u0420\u0435\u0458\u0445\u0430\u043d\u043b\u0438", "name:uk": "\u0420\u0435\u0439\u0445\u0430\u043d\u043b\u0438", "name:ur": "\u0631\u06cc\u062d\u0627\u0646\u0644\u06cc", "name:zh": "\u96f7\u4f0a\u6f22\u52d2", "place": "town", "population": "91974", "population:date": "2016", "salb:adm1name": "Hatay", "salb:adm2name": "Reyhanli", "salb:id": "TUR037009", "wikidata": "Q945375", "wikipedia": "tr:Reyhanl\u0131", "wikipedia:ar": "\u0627\u0644\u0631\u064a\u062d\u0627\u0646\u064a\u0629 (\u0625\u0633\u0643\u0646\u062f\u0631\u0648\u0646)", "wikipedia:tr": "Reyhanl\u0131"}}, {"type": "node", "id": 567062267, "lat": 36.3954821, "lon": 36.6884995, "tags": {"name": "\u062c\u0646\u062f\u064a\u0631\u0633", "name:ar": "\u062c\u0646\u062f\u064a\u0631\u0633", "name:de": "Dschendeiris", "name:en": "Jendairis", "name:fa": "\u062c\u0646\u062f\u06cc\u0631\u0633", "name:fr": "Djendairise", "name:he": "\u05d2\u05f3\u05e0\u05d3\u05d9\u05e8\u05e1", "name:ja": "\u30b8\u30a7\u30f3\u30c7\u30a4\u30ea\u30b9", "name:kmr": "\u062c\u0646\u062f\u0631\u06ce\u0633\u06ce", "name:ko": "\uc820\ub370\uc774\ub9ac\uc2a4", "name:ks": "\u062c\u0646\u062f\u06cc\u0631\u0633", "name:ku": "Cindir\u00eas\u00ea", "name:ml": "\u0d1c\u0d28\u0d4d\u0d26\u0d31\u0d40\u0d38\u0d4d", "name:pnb": "\u062c\u0646\u062f\u06cc\u0631\u0633", "name:ru": "\u0414\u0436\u044d\u043d\u0434\u0430\u0439\u0440\u0438\u0441", "name:tr": "Cinderes", "name:ur": "\u062c\u0646\u062f\u06cc\u0631\u0633", "place": "town", "population": "13661", "population:date": "2004", "source:population": "\u0627\u0644\u0645\u0643\u062a\u0628 \u0627\u0644\u0645\u0631\u0643\u0632\u064a \u0644\u0644\u0625\u062d\u0635\u0627\u0621", "wikidata": "Q950797", "wikipedia": "ar:\u062c\u0646\u062f\u064a\u0631\u0633"}}, {"type": "node", "id": 567062428, "lat": 36.1851068, "lon": 36.720735, "tags": {"name": "\u0633\u0631\u0645\u062f\u0627", "name:ar": "\u0633\u0631\u0645\u062f\u0627", "name:de": "Sarmada", "name:en": "Sarmada", "name:fr": "Sarmada", "name:he": "\u05e1\u05e8\u05de\u05d3\u05d0", "name:ja": "\u30b5\u30eb\u30de\u30c0\u30fc", "name:ko": "\uc0ac\ub974\ub9c8\ub2e4", "name:ml": "\u0d38\u0d7c\u0d2e\u0d26", "name:ru": "\u0421\u0430\u0440\u043c\u0430\u0434\u0430", "place": "town", "population": "11181", "population:date": "2004", "source:population": "\u0627\u0644\u0645\u0643\u062a\u0628 \u0627\u0644\u0645\u0631\u0643\u0632\u064a \u0644\u0644\u0625\u062d\u0635\u0627\u0621", "wikidata": "Q7424272"}}, {"type": "node", "id": 567062622, "lat": 36.2118438, "lon": 36.5207448, "tags": {"name": "\u062d\u0627\u0631\u0645", "name:ar": "\u062d\u0627\u0631\u0645", "name:bg": "\u0425\u0430\u0440\u0438\u043c", "name:de": "Harim", "name:en": "Harim", "name:fa": "\u062d\u0627\u0631\u0645", "name:fr": "Harime", "name:he": "\u05d7\u05d0\u05e8\u05dd", "name:hy": "\u0540\u0561\u0580\u0565\u0574", "name:ja": "\u30cf\u30fc\u30ea\u30e0", "name:ka": "\u10f0\u10d0\u10e0\u10d4\u10db\u10d8", "name:ko": "\ud558\ub9bc", "name:ml": "\u0d39\u0d3e\u0d31\u0d3f\u0d02", "name:ru": "\u0425\u0430\u0440\u0438\u043c", "name:ur": "\u062d\u0627\u0631\u0645", "place": "town", "population": "10019", "population:date": "2004", "source:population": "\u0627\u0644\u0645\u0643\u062a\u0628 \u0627\u0644\u0645\u0631\u0643\u0632\u064a \u0644\u0644\u0625\u062d\u0635\u0627\u0621", "wikidata": "Q771907", "wikipedia": "ar:\u062d\u0627\u0631\u0645"}}, {"type": "node", "id": 571209309, "lat": 36.3604326, "lon": 37.0107567, "tags": {"name": "\u0627\u0644\u0632\u0647\u0631\u0627\u0621", "name:ar": "\u0627\u0644\u0632\u0647\u0631\u0627\u0621", "name:de": "as-Sahraa", "name:en": "Az-Zahra'", "name:fr": "Az-Zahraa", "name:he": "\u05d0-\u05d6\u05d4\u05e8\u05d0\u05d0", "name:ja": "\u30a2\u30c3\u30a0\u30b6\u30d8\u30e9\u30fc", "name:ko": "\uc544\uc790\ud750\ub77c", "name:ku": "Zehra", "name:ml": "\u0d05\u0d38\u0d4d\u0d38\u0d39\u0d4d\u0d31", "name:ru": "\u0410\u0437-\u0417\u0430\u0445\u0440\u0430", "place": "town", "population": "13780", "population:date": "2004", "source:population": "\u0627\u0644\u0645\u0643\u062a\u0628 \u0627\u0644\u0645\u0631\u0643\u0632\u064a \u0644\u0644\u0625\u062d\u0635\u0627\u0621", "wikidata": "Q17408223"}}, {"type": "node", "id": 571209438, "lat": 36.0882709, "lon": 36.7600254, "tags": {"name": "\u0625\u0628\u0651\u064a\u0646", "name:ar": "\u0625\u0628\u0651\u064a\u0646", "name:de": "Ibbin", "name:en": "Ibbin", "name:fr": "Ibbine", "name:he": "\u05d0\u05d9\u05d1\u05d1\u05d9\u05df", "name:ja": "\u30a4\u30c3\u30d3\u30fc\u30f3", "name:ko": "\uc785\uc094", "name:ru": "\u0418\u0431\u0431\u0438\u043d", "place": "town", "population": "6220", "population:date": "2004", "source:population": "\u0627\u0644\u0645\u0643\u062a\u0628 \u0627\u0644\u0645\u0631\u0643\u0632\u064a \u0644\u0644\u0625\u062d\u0635\u0627\u0621a"}}, {"type": "node", "id": 571209441, "lat": 36.376783, "lon": 36.9927752, "tags": {"name": "\u0646\u0628\u0644", "name:ar": "\u0646\u0628\u0644", "name:de": "Nubbul", "name:en": "Nubbul", "name:fr": "Nubbul", "name:he": "\u05e0\u05d1\u05d1\u05dc", "name:ja": "\u30cc\u30c3\u30d6\u30eb", "name:ko": "\ub204\ubfd4", "name:ku": "Nibil", "name:ml": "\u0d28\u0d41\u0d2c\u0d4d\u0d2c\u0d41\u0d7d", "name:ru": "\u041d\u0443\u0431\u0431\u0443\u043b", "place": "town", "population": "21039", "population:date": "2004", "source:population": "\u0627\u0644\u0645\u0643\u062a\u0628 \u0627\u0644\u0645\u0631\u0643\u0632\u064a \u0644\u0644\u0625\u062d\u0635\u0627\u0621", "wikidata": "Q7067856", "wikipedia": "ar:\u0646\u0628\u0644 (\u062d\u0644\u0628)"}}, {"type": "node", "id": 571209504, "lat": 36.1393709, "lon": 36.8234774, "tags": {"name": "\u0627\u0644\u0623\u062a\u0627\u0631\u0628", "name:ar": "\u0627\u0644\u0623\u062a\u0627\u0631\u0628", "name:ckb": "\u0626\u06d5\u062a\u0627\u0631\u0628", "name:cs": "At\u00e1rib", "name:de": "al-Atareb", "name:en": "Al-Atareb", "name:fr": "Al-Atareb", "name:he": "\u05d0\u05dc-\u05d0\u05ea\u05d0\u05e8\u05d1", "name:ja": "\u30a2\u30eb\u30a0\u30a2\u30bf\u30fc\u30ea\u30d6", "name:ko": "\uc54c\uc544\ud0c0\ub808\ube0c", "name:ml": "\u0d05\u0d24\u0d4d\u0d24\u0d3e\u0d31\u0d3f\u0d2c\u0d4d", "name:ru": "\u0410\u043b\u044c-\u0410\u0442\u0430\u0440\u0438\u0431", "name:tr": "Es\u00e2rib", "name:ur": "\u0627\u062a\u0627\u0631\u0628", "name:zh": "\u963f\u5854\u52d2\u5e03", "place": "town", "population": "10657", "population:date": "2004", "source:population": "\u0627\u0644\u0645\u0643\u062a\u0628 \u0627\u0644\u0645\u0631\u0643\u0632\u064a \u0644\u0644\u0625\u062d\u0635\u0627\u0621", "wikidata": "Q4118953", "wikipedia": "fr:Atarib"}}, {"type": "node", "id": 571209713, "lat": 36.2824921, "lon": 36.8520069, "tags": {"name": "\u062f\u0627\u0631\u0629 \u0639\u0632\u0629", "name:ar": "\u062f\u0627\u0631\u0629 \u0639\u0632\u0629", "name:de": "Daret Issa", "name:en": "Daret Izza", "name:fr": "Darete Izza", "name:he": "\u05d3\u05d0\u05e8\u05ea \u05e2\u05d6\u05d6\u05d4", "name:ja": "\u30c0\u30fc\u30ec\u30c8\u30fb\u30a4\u30c3\u30b6", "name:ko": "\ub2e4\ub808\ud2b8\uc78a\uc9dc", "name:ku": "Deraz\u00ea", "name:ml": "\u0d26\u0d3e\u0d31\u0d24\u0d4d\u0d24\u0d4d \u0d07\u0d38\u0d4d\u0d38", "name:ru": "\u0414\u0430\u0440\u0435\u0442-\u0418\u0437\u0437\u0430", "place": "town", "population": "13525", "population:date": "2004", "source:population": "\u0627\u0644\u0645\u0643\u062a\u0628 \u0627\u0644\u0645\u0631\u0643\u0632\u064a \u0644\u0644\u0625\u062d\u0635\u0627\u0621", "wikidata": "Q12211294"}}, {"type": "node", "id": 571210104, "lat": 36.1166667, "lon": 36.5166667, "tags": {"name": "\u0643\u0641\u0631 \u062a\u062e\u0627\u0631\u064a\u0645", "name:ar": "\u0643\u0641\u0631 \u062a\u062e\u0627\u0631\u064a\u0645", "name:de": "Kafr Tacharim", "name:en": "Kafr Takharim", "name:fr": "Kafr Takharim", "name:he": "\u05db\u05e4\u05e8 \u05ea\u05d7\u05f3\u05d0\u05e8\u05d9\u05dd", "name:ja": "\u30ab\u30d5\u30eb\u30fb\u30bf\u30cf\u30fc\u30ea\u30e0", "name:ko": "\uce74\ud504\ub974\ud0c0\uce74\ub9bc", "name:ru": "\u041a\u0430\u0444\u0440-\u0422\u0430\u0445\u0430\u0440\u0438\u043c", "place": "town", "population": "10084", "population:date": "2004", "source:population": "\u0627\u0644\u0645\u0643\u062a\u0628 \u0627\u0644\u0645\u0631\u0643\u0632\u064a \u0644\u0644\u0625\u062d\u0635\u0627\u0621", "wikidata": "Q4120373"}}, {"type": "node", "id": 571210112, "lat": 36.2642792, "lon": 36.9494636, "tags": {"name": "\u0642\u0628\u062a\u0627\u0646 \u0627\u0644\u062c\u0628\u0644", "name:ar": "\u0642\u0628\u062a\u0627\u0646 \u0627\u0644\u062c\u0628\u0644", "name:de": "Kubtan al-Dschabal", "name:en": "Qubtan al-Jabal", "name:fr": "Qubtan al-Djabal", "name:ku": "Qebtan El-Cebel", "name:ml": "\u0d16\u0d41\u0d2c\u0d4d\u0d24\u0d3e\u0d7b \u0d05\u0d7d-\u0d1c\u0d2c\u0d7d", "name:ru": "\u041a\u0443\u0431\u0442\u0430\u043d-\u0430\u043b\u044c-\u0414\u0436\u0430\u0431\u0430\u043b\u044c", "place": "town", "population": "5285", "population:date": "2004", "source": "\u0627\u0644\u0645\u0643\u062a\u0628 \u0627\u0644\u0645\u0631\u0643\u0632\u064a \u0644\u0644\u0625\u062d\u0635\u0627\u0621"}}, {"type": "node", "id": 571210148, "lat": 36.1494976, "lon": 36.9469626, "tags": {"name": "\u0623\u0648\u0631\u0645 \u0627\u0644\u0643\u0628\u0631\u0649", "name:ar": "\u0623\u0648\u0631\u0645 \u0627\u0644\u0643\u0628\u0631\u0649", "name:de": "Orum al-Kubra", "name:en": "Orum al-Kubra", "name:fr": "Orum al-Kubra", "name:he": "\u05d0\u05d5\u05e8\u05d5\u05dd \u05d0\u05dc-\u05db\u05d5\u05d1\u05e8\u05d0", "name:ja": "\u30aa\u30eb\u30e0\u30fb\u30a2\u30eb\u30a0\u30af\u30d6\u30e9", "name:ko": "\uc624\ub8f8\uc54c\ucfe0\ube0c\ub77c", "name:ml": "\u0d13\u0d31\u0d41\u0d02 \u0d05\u0d7d \u0d15\u0d41\u0d2c\u0d4d\u0d30", "name:ru": "\u041e\u0440\u0443\u043c-\u0430\u043b\u044c-\u041a\u0443\u0431\u0440\u0430", "place": "town", "population": "5391", "population:date": "2004", "source:population": "\u0627\u0644\u0645\u0643\u062a\u0628 \u0627\u0644\u0645\u0631\u0643\u0632\u064a \u0644\u0644\u0625\u062d\u0635\u0627\u0621"}}, {"type": "node", "id": 571210198, "lat": 36.2135713, "lon": 36.7704347, "tags": {"name": "\u0627\u0644\u062f\u0627\u0646\u0627", "name:ar": "\u0627\u0644\u062f\u0627\u0646\u0627", "name:de": "ad-Dana", "name:en": "Ad-Dana", "name:fr": "Ad-Dana", "name:he": "\u05d0-\u05d3\u05d0\u05e0\u05d0", "name:ja": "\u30a2\u30c3\u30a0\u30c0\u30fc\u30ca", "name:ko": "\uc544\ub2e4\ub098", "name:ml": "\u0d05\u0d26\u0d4d\u0d26\u0d3e\u0d28", "name:ru": "\u0410\u0434-\u0414\u0430\u043d\u0430", "place": "town", "population": "14208", "population:date": "2004", "source:population": "\u0627\u0644\u0645\u0643\u062a\u0628 \u0627\u0644\u0645\u0631\u0643\u0632\u064a \u0644\u0644\u0625\u062d\u0635\u0627\u0621", "wikidata": "Q4702330"}}, {"type": "node", "id": 571210369, "lat": 36.1105751, "lon": 36.695017, "tags": {"name": "\u0643\u0644\u0644\u064a", "name:ar": "\u0643\u0644\u0644\u064a", "name:de": "Killi", "name:en": "Killi", "name:fr": "Cilli", "name:he": "\u05db\u05dc\u05dc\u05d9", "name:ja": "\u30ad\u30c3\u30ea", "name:ko": "\ud0ac\ub9ac", "name:ru": "\u041a\u0438\u043b\u043b\u0438", "place": "town", "population": "7157", "population:date": "2004", "source:population": "\u0627\u0644\u0645\u0643\u062a\u0628 \u0627\u0644\u0645\u0631\u0643\u0632\u064a \u0644\u0644\u0625\u062d\u0635\u0627\u0621"}}, {"type": "node", "id": 571210387, "lat": 36.2287502, "lon": 36.8158787, "tags": {"name": "\u062a\u0631\u0645\u0627\u0646\u064a\u0646", "name:ar": "\u062a\u0631\u0645\u0627\u0646\u064a\u0646", "name:de": "Termanin", "name:en": "Termanin", "name:fr": "Termanine", "name:he": "\u05ea\u05e8\u05de\u05d0\u05e0\u05d9\u05df", "name:ja": "\u30c6\u30eb\u30de\u30fc\u30cb\u30f3", "name:ko": "\ud14c\ub974\ub9cc\uc778", "name:ml": "\u0d24\u0d7c\u0d2e\u0d3e\u0d28\u0d40\u0d7b", "name:ru": "\u0422\u0435\u0440\u043c\u0430\u043d\u0438\u043d", "place": "town", "population": "10394", "population:date": "2004", "source:population": "\u0627\u0644\u0645\u0643\u062a\u0628 \u0627\u0644\u0645\u0631\u0643\u0632\u064a \u0644\u0644\u0625\u062d\u0635\u0627\u0621", "wikidata": "Q1183365"}}, {"type": "node", "id": 571210397, "lat": 36.1596437, "lon": 36.819894, "tags": {"name": "\u0645\u0639\u0631\u0629 \u0627\u0644\u0623\u062a\u0627\u0631\u0628", "name:ar": "\u0645\u0639\u0631\u0629 \u0627\u0644\u0623\u062a\u0627\u0631\u0628", "name:de": "Maarrat al-Atarib", "name:en": "Ma'arrat al-Atarib", "name:fr": "Maarrate al-Atarib", "name:he": "\u05de\u05e2\u05e8\u05ea \u05d0\u05dc-\u05d0\u05ea\u05d0\u05e8\u05d1", "name:ja": "\u30de\u30a2\u30c3\u30e9\u30c8\u30fb\u30a2\u30eb\u30a0\u30a2\u30bf\u30fc\u30ea\u30d6", "name:ko": "\ub9c8\uc544\ub77c\ud2b8\uc54c\uc544\ud0c0\ub9ac\ube0c", "name:ml": "\u0d2e\u0d3e\u0d31\u0d24\u0d4d\u0d24\u0d4d \u0d05\u0d7d-\u0d05\u0d24\u0d4d\u0d24\u0d3e\u0d31\u0d3f\u0d2c\u0d4d", "name:ru": "\u041c\u0430\u0430\u0440\u0440\u0430\u0442-\u0430\u043b\u044c-\u0410\u0442\u0430\u0440\u0438\u0431", "place": "town", "population": "5796", "population:date": "2004", "source:population": "\u0627\u0644\u0645\u0643\u062a\u0628 \u0627\u0644\u0645\u0631\u0643\u0632\u064a \u0644\u0644\u0625\u062d\u0635\u0627\u0621"}}, {"type": "node", "id": 571210512, "lat": 36.2530871, "lon": 36.8019784, "tags": {"name": "\u062a\u0644\u0639\u0627\u062f\u0629", "name:ar": "\u062a\u0644\u0639\u0627\u062f\u0629", "name:de": "Tallada", "name:en": "Tall'ada", "name:fr": "Tallada", "name:he": "\u05ea\u05dc\u05e2\u05d0\u05d3\u05d4", "name:ja": "\u30bf\u30c3\u30eb\u30a2\u30fc\u30c0", "name:ko": "\ud0c8\ub77c\ub2e4", "name:ru": "\u0422\u0430\u043b\u043b\u0430\u0434\u0430", "place": "town", "population": "5599", "population:date": "2004", "source:population": "\u0627\u0644\u0645\u0643\u062a\u0628 \u0627\u0644\u0645\u0631\u0643\u0632\u064a \u0644\u0644\u0625\u062d\u0635\u0627\u0621"}}]}