{"version": 0.6, "generator": "Overpass API 0.7.62.4 2390de5a", "osm3s": {"timestamp_osm_base": "2025-01-08T07:29:58Z", "copyright": "The data included in this document is from www.openstreetmap.org. The data is made available under ODbL."}, "elements": [{"type": "node", "id": 4361712887, "lat": 7.3021412, "lon": 45.4369244, "tags": {"name": "Daratoole", "place": "town"}}, {"type": "node", "id": 7318068709, "lat": 7.3200126, "lon": 45.6826426, "tags": {"name": "Toon Barwaaqo", "place": "city"}}, {"type": "node", "id": 11586198707, "lat": 7.2317132, "lon": 45.5049452, "tags": {"name": "Dhagxanya Cado", "place": "town"}}, {"type": "node", "id": 12023754969, "lat": 7.2696731, "lon": 45.6971168, "tags": {"place": "town"}}]}