{"version": 0.6, "generator": "Overpass API 0.7.62.4 2390de5a", "osm3s": {"timestamp_osm_base": "2025-01-08T07:09:35Z", "copyright": "The data included in this document is from www.openstreetmap.org. The data is made available under ODbL."}, "elements": [{"type": "node", "id": 463218174, "lat": 35.53032, "lon": 1.0237833, "tags": {"name": "Rahouia", "name:ar": "\u0631\u062d\u0648\u064a\u0629", "name:ber": "\u2d54\u2d3b\u2d43\u2d61\u2d49\u2d62\u2d62\u2d30", "name:en": "Rahouia", "name:fr": "Rahouia", "name:kab": "Rre\u1e25weyya", "old_name": "Montgolfier", "place": "town", "population": "24983", "wikidata": "Q1649911", "wikipedia": "en:Rahouia"}}, {"type": "node", "id": 464067879, "lat": 35.4552913, "lon": 0.687517, "tags": {"name": "Oued El Abtal", "name:ar": "\u0648\u0627\u062f\u064a \u0627\u0644\u0623\u0628\u0637\u0627\u0644", "name:ber": "\u2d61\u2d30\u2d37 \u2d3b\u2d4d \u2d30\u2d31\u2d5f\u2d30\u2d4d", "name:en": "Oued El Abtal", "name:fr": "Oued El Abtal", "name:kab": "Wad Leb\u1e6dal", "old_name": "Uzes-le-Duc", "place": "town", "population": "21278", "population:date": "2008", "wikidata": "Q3358012", "wikimedia_commons": "Category:Oued El Abtal", "wikipedia": "fr:Oued El Abtal"}}, {"type": "node", "id": 929382990, "lat": 35.3848636, "lon": 1.0544339, "tags": {"name": "Mechraa Safa", "name:ar": "\u0645\u0634\u0631\u0639 \u0627\u0644\u0635\u0641\u0627\u0621", "name:ber": "\u2d4e\u2d3b\u2d5b\u2d54\u2d3b\u2d44 \u2d5a\u2d5a\u2d3c\u2d30", "name:en": "Mechraa Safa", "name:fr": "Mechraa Safa", "name:kab": "Mecre\u025b \u1e62\u1e63fa", "place": "town", "population": "16077", "wikidata": "Q1649372", "wikipedia": "ar:\u0645\u0634\u0631\u0639 \u0627\u0644\u0635\u0641\u0627\u0621"}}]}