{"version": 0.6, "generator": "Overpass API 0.7.62.4 2390de5a", "osm3s": {"timestamp_osm_base": "2025-01-08T06:28:44Z", "copyright": "The data included in this document is from www.openstreetmap.org. The data is made available under ODbL."}, "elements": [{"type": "node", "id": 248154948, "lat": 36.5269242, "lon": 37.9559288, "tags": {"alt_name:tr": "M\u00fcnbi\u00e7", "name": "\u0645\u0646\u0628\u062c", "name:ar": "\u0645\u0646\u0628\u062c", "name:ckb": "\u0645\u0646\u0628\u062c", "name:cs": "Manbid\u017e", "name:de": "Manbidsch", "name:el": "\u039c\u03b5\u03bc\u03b2\u03af\u03c4\u03b6", "name:en": "Manbij", "name:es": "Manbij", "name:eu": "Manbij", "name:fr": "Menbidj", "name:he": "\u05de\u05e0\u05d1\u05d9\u05d2'", "name:hi": "\u092e\u0928\u092c\u093f\u091c", "name:hy": "\u0544\u0561\u0576\u0562\u056b\u057b", "name:ja": "\u30de\u30f3\u30d3\u30b8", "name:ko": "\ub9cc\ube44\uc988", "name:ku": "Minbic", "name:ml": "\u0d2e\u0d7b\u0d2c\u0d3f\u0d1c\u0d4d", "name:ru": "\u041c\u0430\u043d\u0431\u0438\u0434\u0436", "name:tr": "Menbi\u00e7", "name:uk": "\u041c\u0430\u043d\u0431\u0456\u0434\u0436", "name:zh": "\u66fc\u6bd4\u5b63", "old_name": "Mabbog;Hi\u00e9rapolis Bambyce", "place": "city", "population": "99497", "population:date": "2004", "source:population": "\u0627\u0644\u0645\u0643\u062a\u0628 \u0627\u0644\u0645\u0631\u0643\u0632\u064a \u0644\u0644\u0625\u062d\u0635\u0627\u0621", "wikidata": "Q1146939", "wikipedia": "ar:\u0645\u0646\u0628\u062c"}}, {"type": "node", "id": 961669400, "lat": 36.8319843, "lon": 37.9994474, "tags": {"alt_name": "Kargam\u0131\u015f", "name": "Karkam\u0131\u015f", "name:ar": "\u0643\u0631\u0643\u0645\u064a\u0634", "name:ce": "\u041a\u0430\u0440\u043a\u0430\u043c\u0438\u0448", "name:ckb": "\u06af\u0631\u06af\u0627\u0645\u06ce\u0634", "name:fa": "\u06a9\u0627\u0631\u06a9\u0627\u0645\u0634", "name:hy": "\u0543\u0561\u0580\u0561\u057a\u056c\u0578\u0582\u057d", "name:ku": "Girgam\u00ea\u015f", "name:ml": "\u0d15\u0d3e\u0d7c\u0d15\u0d4d\u0d15\u0d46\u0d2e\u0d3f\u0d37\u0d4d", "name:ru": "\u041a\u0430\u0440\u043a\u0430\u043c\u044b\u0448", "name:sr": "\u041a\u0430\u0440\u043a\u0430\u043c\u0438\u0448", "name:ur": "\u06a9\u0627\u0631\u06a9\u0627\u0645\u0634", "place": "town", "population": "10436", "population:date": "2018", "wikidata": "Q1018531", "wikipedia": "tr:Karkam\u0131\u015f"}}, {"type": "node", "id": 3586671408, "lat": 36.7827817, "lon": 38.0472641, "tags": {"name": "\u0634\u064a\u0648\u062e \u0641\u0648\u0642\u0627\u0646\u064a", "name:ar": "\u0634\u064a\u0648\u062e \u0641\u0648\u0642\u0627\u0646\u064a", "name:de": "Schujoch Fokani", "name:en": "Shuyukh Fouqani", "name:fr": "Chioukh Fouqani", "name:he": "\u05e9\u05d9\u05d5\u05d7\u05f3 \u05e4\u05d5\u05e7\u05d0\u05e0\u05d9", "name:ja": "\u30b7\u30e5\u30e6\u30fc\u30af\u30fb\u30d5\u30a9\u30ab\u30fc\u30cb", "name:ko": "\uc288\uc720\ud06c\ud3ec\uce74\ub2c8", "name:ml": "\u0d2b\u0d4b\u0d16\u0d3e\u0d28\u0d3f", "name:ru": "\u0428\u0443\u044e\u0445-\u0424\u043e\u043a\u0430\u043d\u0438", "place": "town", "population": "9303", "population:date": "2004", "source:population": "\u0627\u0644\u0645\u0643\u062a\u0628 \u0627\u0644\u0645\u0631\u0643\u0632\u064a \u0644\u0644\u0625\u062d\u0635\u0627\u0621"}}, {"type": "node", "id": 3871242688, "lat": 36.8181146, "lon": 38.0098306, "tags": {"alt_name:ku": "Kaniya Dil", "name": "\u062c\u0631\u0627\u0628\u0644\u0633", "name:ar": "\u062c\u0631\u0627\u0628\u0644\u0633", "name:ckb": "\u062c\u06d5\u0631\u0627\u0628\u0644\u0648\u0648\u0633", "name:cs": "D\u017ear\u00e1bulus", "name:de": "Dscharablus", "name:en": "Jarablus", "name:es": "Yarabulus", "name:fr": "Djarablus", "name:he": "\u05d2\u05f3\u05e8\u05d0\u05d1\u05dc\u05e1", "name:hy": "\u054b\u0561\u0580\u0561\u0562\u0578\u0582\u056c\u0578\u0582\u057d", "name:ja": "\u30b8\u30e3\u30e9\u30fc\u30d6\u30eb\u30b9", "name:ko": "\uc790\ub77c\ubd88\ub8e8\uc2a4", "name:ku": "Cerabl\u00fbs", "name:ml": "\u0d1c\u0d30\u0d3e\u0d2c\u0d41\u0d32\u0d41\u0d38\u0d4d", "name:ru": "\u0414\u0436\u0430\u0440\u0430\u0431\u043b\u0443\u0441", "name:tr": "Cerablus", "name:zh": "\u8d3e\u62c9\u5e03\u9c81\u65af", "place": "town", "population": "11570", "population:date": "2004", "source:population": "\u0627\u0644\u0645\u0643\u062a\u0628 \u0627\u0644\u0645\u0631\u0643\u0632\u064a \u0644\u0644\u0625\u062d\u0635\u0627\u0621", "wikidata": "Q1149502"}}]}