{"version": 0.6, "generator": "Overpass API 0.7.62.4 2390de5a", "osm3s": {"timestamp_osm_base": "2025-01-08T06:40:59Z", "copyright": "The data included in this document is from www.openstreetmap.org. The data is made available under ODbL."}, "elements": [{"type": "node", "id": 4116845005, "lat": 18.5046499, "lon": 30.6330833, "tags": {"GNS:dsg_code": "PPL", "GNS:dsg_name": "populated place", "GNS:id": "-2206", "GNS:modify_date": "2009-08-18", "alt_name": "Al Qulayd Bahri;Goled Bahri;El Goled Bahri;Al Qolid Bahri;El Guleid Bahri;Al Qulayd Ba\u1e29r\u012b", "alt_name:ar": "\u0627\u0644\u0642\u0648\u0644\u062f \u0628\u0647\u0631;\u0627\u0644\u0642\u0644\u064a\u062f \u0628\u062d\u0631\u064a", "alt_name:en": "Al Qulayd Bahri", "name": "\u0627\u0644\u0642\u0648\u0644\u062f", "name:ar": "\u0627\u0644\u0642\u0648\u0644\u062f", "name:en": "Al Goled", "name:fr": "Al Goled", "place": "city", "wikidata": "Q12191556"}}]}