{"version": 0.6, "generator": "Overpass API 0.7.62.4 2390de5a", "osm3s": {"timestamp_osm_base": "2025-01-08T07:31:59Z", "copyright": "The data included in this document is from www.openstreetmap.org. The data is made available under ODbL."}, "elements": [{"type": "node", "id": 1404227986, "lat": 11.16027, "lon": 48.19487, "tags": {"alt_name": "Laasqorey;Lasqoray;Las Qorei;Las Khorey;Las Khoreh;Las Koreh", "name": "Laasqoray \u0644\u0627\u0633\u0642\u0631\u0649", "name:ar": "\u0644\u0627\u0633\u0642\u0631\u0649", "name:ca": "Las Khoray", "name:de": "Laasqorey", "name:en": "Las Khorey", "name:fr": "Las Khorey", "name:it": "Las Gorei", "name:pl": "Laasqoray", "name:ur": "\u0644\u0627\u0633 \u0642\u0631\u06cc", "name:zu": "Las Khorey", "pcode": "NC-3901-W05-001", "place": "town", "source": "UNDP - 2006, GTZ - 2002, UNDP - 1997", "wikidata": "Q1017225", "wikipedia": "so:Laasqoray"}}]}