{"version": 0.6, "generator": "Overpass API 0.7.62.4 2390de5a", "osm3s": {"timestamp_osm_base": "2025-01-08T07:11:40Z", "copyright": "The data included in this document is from www.openstreetmap.org. The data is made available under ODbL."}, "elements": [{"type": "node", "id": 424087266, "lat": 34.9506637, "lon": -1.3667337, "tags": {"name": "Hennaya", "name:ar": "\u0627\u0644\u062d\u0646\u0627\u064a\u0629", "name:ber": "\u2d4d\u2d3b\u2d43\u2d4f\u2d30\u2d62\u2d30", "name:el": "\u03a7\u03b5\u03bd\u03bd\u03ac\u03b3\u03b9\u03b1", "name:en": "Hennaya", "name:fr": "Hennaya", "name:kab": "Hennaya", "old_name": "Eug\u00e8ne \u00c9tienne", "place": "town", "population": "33356", "ref:ONS": "1326", "wikidata": "Q3130297", "wikimedia_commons": "Category:Hennaya", "wikipedia": "fr:Hennaya"}}, {"type": "node", "id": 424090451, "lat": 34.6403022, "lon": -1.3220383, "tags": {"name": "Sebdou", "name:ar": "\u0633\u0628\u062f\u0648", "name:ber": "\u2d59\u2d3b\u2d31\u2d37\u2d53", "name:en": "Sebdou", "name:fr": "Sebdou", "name:kab": "Sebdu", "place": "town", "population": "39800", "wikidata": "Q1649930", "wikimedia_commons": "Category:Sebdou", "wikipedia": "fr:Sebdou"}}, {"type": "node", "id": 439902538, "lat": 34.904794, "lon": -1.0281674, "tags": {"name": "Ouled Mimoun", "name:ar": "\u0623\u0648\u0644\u0627\u062f \u0645\u064a\u0645\u0648\u0646", "name:ber": "\u2d61\u2d4d\u2d30\u2d37 \u2d4e\u2d49\u2d4e\u2d53\u2d4f", "name:en": "Ouled Mimoun", "name:fr": "Ouled Mimoun", "name:kab": "Wlad Mimun", "place": "town", "population": "26389", "ref:ONS": "1313", "wikidata": "Q2110236", "wikimedia_commons": "Category:Ouled Mimoun", "wikipedia": "fr:Ouled Mimoun"}}, {"type": "node", "id": 439911463, "lat": 34.8260248, "lon": -1.530335, "tags": {"name": "Sabra", "name:ar": "\u0635\u0628\u0631\u0629", "name:ber": "\u2d5a\u2d30\u2d31\u2d54\u2d30", "name:en": "Sabra", "name:fr": "Sabra", "name:kab": "\u1e62ebra", "old_name": "Turenne", "place": "town", "population": "28555", "wikidata": "Q3108345", "wikimedia_commons": "Category:Sabra (Tlemcen Province)", "wikipedia": "fr:Sabra (Tlemcen)"}}, {"type": "node", "id": 841797699, "lat": 34.8733172, "lon": -1.3302647, "tags": {"name": "Mansourah", "name:ar": "\u0645\u0646\u0635\u0648\u0631\u0629", "name:ber": "\u2d4e\u2d3b\u2d4f\u2d59\u2d53\u2d54\u2d30", "name:en": "Mansourah", "name:fr": "Mansourah", "name:kab": "Men\u1e63ura", "place": "town", "population": "49150", "wikidata": "Q3286584", "wikimedia_commons": "Category:Mansourah", "wikipedia": "fr:Mansourah (Tlemcen)"}}, {"type": "node", "id": 841838477, "lat": 35.0472865, "lon": -1.3739319, "tags": {"name": "A\u00efn Youcef", "name:ar": "\u0639\u064a\u0646 \u064a\u0648\u0633\u0641", "name:ber": "\u2d44\u2d49\u2d4f \u2d62\u2d53\u2d59\u2d3b\u2d3c", "name:el": "\u0391\u0390\u03bd \u0393\u03b9\u03bf\u03c5\u03c3\u03ad\u03c6", "name:en": "Ain Youcef", "name:fr": "A\u00efn Youcef", "name:kab": "\u0190in Yusef", "old_name": "Lavayssi\u00e8re", "place": "town", "population": "13234", "wikidata": "Q1648923", "wikimedia_commons": "Category:A\u00efn Youcef", "wikipedia": "fr:A\u00efn Youcef"}}, {"type": "node", "id": 3110093634, "lat": 34.881789, "lon": -1.316699, "tags": {"capital": "4", "name": "Tlemcen \u2d5c\u2d30\u2d4d\u2d30 \u2d49\u2d4e\u2d59\u2d30\u2d4f \u062a\u0644\u0645\u0633\u0627\u0646", "name:an": "Termic\u00e9n", "name:ar": "\u062a\u0644\u0645\u0633\u0627\u0646", "name:ber": "\u2d5c\u2d30\u2d4d\u2d30 \u2d49\u2d4e\u2d59\u2d30\u2d4f", "name:el": "\u03a4\u03bb\u03ad\u03bc\u03c3\u03b5\u03bd", "name:en": "Tlemcen", "name:es": "Tremec\u00e9n", "name:fr": "Tlemcen", "name:he": "\u05ea\u05dc\u05de\u05e1\u05d0\u05df", "name:it": "Tlemcen", "name:ja": "\u30c8\u30ec\u30e0\u30bb\u30f3", "name:kab": "Tlemsan", "name:ko": "\ud2c0\ub818\uc13c", "name:lt": "Tlemsenas", "name:ru": "\u0422\u043b\u0435\u043c\u0441\u0435\u043d", "name:tr": "Tilimsan", "name:zh": "\u7279\u83b1\u59c6\u68ee", "place": "city", "population": "140158", "wikidata": "Q185134", "wikipedia": "fr:Tlemcen"}}, {"type": "node", "id": 4520491165, "lat": 34.9207591, "lon": -1.2910642, "tags": {"name": "Chetouane", "name:ar": "\u0634\u062a\u0648\u0627\u0646", "name:ber": "\u2d5b\u2d3b\u2d5c\u2d61\u2d30\u2d4f", "name:el": "\u03a4\u03c3\u03b5\u03c4\u03bf\u03c5\u03b1\u03bd\u03ad", "name:en": "Chetouane", "name:fr": "Chetouane", "name:kab": "Ce\u1e6dwan", "old_name": "N\u00e9grier", "place": "town", "population": "47600", "wikidata": "Q2962883", "wikimedia_commons": "Category:Chetouane", "wikipedia": "fr:Chetouane"}}]}